[{"name":"meta_request.log","payload":{"filename":"c:/work/adusu_std/app/helpers/sessions_helper.rb","line":10,"method":"current_user","message":"  \u001b[1m\u001b[36mUser Load (0.3ms)\u001b[0m  \u001b[1m\u001b[34mSELECT \"users\".* FROM \"users\" WHERE \"users\".\"id\" = $1 LIMIT $2\u001b[0m  [[\"id\", 5], [\"LIMIT\", 1]]","level":"debug"},"time":0,"transaction_id":0,"end":0,"children":[],"cpu_time_start":0,"cpu_time_finish":0,"allocation_count_start":0,"allocation_count_finish":0,"duration":0.0},{"name":"meta_request.log","payload":{"filename":"c:/work/adusu_std/app/helpers/sessions_helper.rb","line":10,"method":"current_user","message":"  ↳ app/helpers/sessions_helper.rb:10:in `current_user'","level":"debug"},"time":0,"transaction_id":0,"end":0,"children":[],"cpu_time_start":0,"cpu_time_finish":0,"allocation_count_start":0,"allocation_count_finish":0,"duration":0.0},{"name":"sql.active_record","payload":{"sql":"SELECT \"users\".* FROM \"users\" WHERE \"users\".\"id\" = $1 LIMIT $2","name":"User Load","binds":[{"name":"id","value_before_type_cast":5,"type":{"precision":null,"scale":null,"limit":4,"range":"-2147483648...2147483648"},"original_attribute":null,"value":5,"value_for_database":5},{"name":"LIMIT","value_before_type_cast":1,"type":{"precision":null,"scale":null,"limit":null},"original_attribute":null,"value":1}],"type_casted_binds":[5,1],"statement_name":"a6","connection":"Not JSON Encodable","filename":"c:/work/adusu_std/app/helpers/sessions_helper.rb","line":10,"method":"current_user"},"time":"2023-09-25T15:42:39.661+09:00","transaction_id":"66b1d48612a4b8ef2874","end":"2023-09-25T15:42:39.663+09:00","children":[],"cpu_time_start":0,"cpu_time_finish":0,"allocation_count_start":0,"allocation_count_finish":0,"duration":1.5424},{"name":"meta_request.log","payload":{"filename":"c:/work/adusu_std/app/controllers/delivery_slip_detail_large_classifications_controller.rb","line":194,"method":"get_public_flag","message":"  \u001b[1m\u001b[36mDeliverySlipHeader Load (0.5ms)\u001b[0m  \u001b[1m\u001b[34mSELECT \"delivery_slip_headers\".* FROM \"delivery_slip_headers\" WHERE \"delivery_slip_headers\".\"id\" = $1 ORDER BY \"delivery_slip_headers\".\"id\" ASC LIMIT $2\u001b[0m  [[\"id\", 1471], [\"LIMIT\", 1]]","level":"debug"},"time":0,"transaction_id":0,"end":0,"children":[],"cpu_time_start":0,"cpu_time_finish":0,"allocation_count_start":0,"allocation_count_finish":0,"duration":0.0},{"name":"meta_request.log","payload":{"filename":"c:/work/adusu_std/app/controllers/delivery_slip_detail_large_classifications_controller.rb","line":194,"method":"get_public_flag","message":"  ↳ app/controllers/delivery_slip_detail_large_classifications_controller.rb:194:in `get_public_flag'","level":"debug"},"time":0,"transaction_id":0,"end":0,"children":[],"cpu_time_start":0,"cpu_time_finish":0,"allocation_count_start":0,"allocation_count_finish":0,"duration":0.0},{"name":"sql.active_record","payload":{"sql":"SELECT \"delivery_slip_headers\".* FROM \"delivery_slip_headers\" WHERE \"delivery_slip_headers\".\"id\" = $1 ORDER BY \"delivery_slip_headers\".\"id\" ASC LIMIT $2","name":"DeliverySlipHeader Load","binds":[{"name":"id","value_before_type_cast":"1471","type":{"precision":null,"scale":null,"limit":4,"range":"-2147483648...2147483648"},"original_attribute":null,"_unboundable":null,"value":"1471","value_for_database":1471},{"name":"LIMIT","value_before_type_cast":1,"type":{"precision":null,"scale":null,"limit":null},"original_attribute":null,"value":1}],"type_casted_binds":[1471,1],"statement_name":"a8","connection":"Not JSON Encodable","filename":"c:/work/adusu_std/app/controllers/delivery_slip_detail_large_classifications_controller.rb","line":194,"method":"get_public_flag"},"time":"2023-09-25T15:42:39.664+09:00","transaction_id":"66b1d48612a4b8ef2874","end":"2023-09-25T15:42:39.666+09:00","children":[],"cpu_time_start":0,"cpu_time_finish":0,"allocation_count_start":0,"allocation_count_finish":0,"duration":1.4582},{"name":"meta_request.log","payload":{"filename":"c:/work/adusu_std/app/controllers/delivery_slip_detail_large_classifications_controller.rb","line":198,"method":"get_public_flag","message":"  \u001b[1m\u001b[36mCustomerMaster Load (0.5ms)\u001b[0m  \u001b[1m\u001b[34mSELECT \"customer_masters\".* FROM \"customer_masters\" WHERE \"customer_masters\".\"id\" = $1 LIMIT $2\u001b[0m  [[\"id\", 86], [\"LIMIT\", 1]]","level":"debug"},"time":0,"transaction_id":0,"end":0,"children":[],"cpu_time_start":0,"cpu_time_finish":0,"allocation_count_start":0,"allocation_count_finish":0,"duration":0.0},{"name":"meta_request.log","payload":{"filename":"c:/work/adusu_std/app/controllers/delivery_slip_detail_large_classifications_controller.rb","line":198,"method":"get_public_flag","message":"  ↳ app/controllers/delivery_slip_detail_large_classifications_controller.rb:198:in `get_public_flag'","level":"debug"},"time":0,"transaction_id":0,"end":0,"children":[],"cpu_time_start":0,"cpu_time_finish":0,"allocation_count_start":0,"allocation_count_finish":0,"duration":0.0},{"name":"sql.active_record","payload":{"sql":"SELECT \"customer_masters\".* FROM \"customer_masters\" WHERE \"customer_masters\".\"id\" = $1 LIMIT $2","name":"CustomerMaster Load","binds":[{"name":"id","value_before_type_cast":86,"type":{"precision":null,"scale":null,"limit":4,"range":"-2147483648...2147483648"},"original_attribute":null,"value":86,"value_for_database":86},{"name":"LIMIT","value_before_type_cast":1,"type":{"precision":null,"scale":null,"limit":null},"original_attribute":null,"value":1}],"type_casted_binds":[86,1],"statement_name":"a5","connection":"Not JSON Encodable","filename":"c:/work/adusu_std/app/controllers/delivery_slip_detail_large_classifications_controller.rb","line":198,"method":"get_public_flag"},"time":"2023-09-25T15:42:39.666+09:00","transaction_id":"66b1d48612a4b8ef2874","end":"2023-09-25T15:42:39.668+09:00","children":[],"cpu_time_start":0,"cpu_time_finish":0,"allocation_count_start":0,"allocation_count_finish":0,"duration":1.642},{"name":"meta_request.log","payload":{"filename":"c:/work/adusu_std/app/controllers/application_controller.rb","line":372,"method":"app_get_session_user","message":"  \u001b[1m\u001b[36mUser Load (0.7ms)\u001b[0m  \u001b[1m\u001b[34mSELECT \"users\".* FROM \"users\" WHERE (id = 5) ORDER BY \"users\".\"id\" ASC LIMIT $1\u001b[0m  [[\"LIMIT\", 1]]","level":"debug"},"time":0,"transaction_id":0,"end":0,"children":[],"cpu_time_start":0,"cpu_time_finish":0,"allocation_count_start":0,"allocation_count_finish":0,"duration":0.0},{"name":"meta_request.log","payload":{"filename":"c:/work/adusu_std/app/controllers/application_controller.rb","line":372,"method":"app_get_session_user","message":"  ↳ app/controllers/application_controller.rb:372:in `app_get_session_user'","level":"debug"},"time":0,"transaction_id":0,"end":0,"children":[],"cpu_time_start":0,"cpu_time_finish":0,"allocation_count_start":0,"allocation_count_finish":0,"duration":0.0},{"name":"sql.active_record","payload":{"sql":"SELECT \"users\".* FROM \"users\" WHERE (id = 5) ORDER BY \"users\".\"id\" ASC LIMIT $1","name":"User Load","binds":[{"name":"LIMIT","value_before_type_cast":1,"type":{"precision":null,"scale":null,"limit":null},"original_attribute":null,"value":1}],"type_casted_binds":[1],"statement_name":null,"connection":"Not JSON Encodable","filename":"c:/work/adusu_std/app/controllers/application_controller.rb","line":372,"method":"app_get_session_user"},"time":"2023-09-25T15:42:39.669+09:00","transaction_id":"66b1d48612a4b8ef2874","end":"2023-09-25T15:42:39.671+09:00","children":[],"cpu_time_start":0,"cpu_time_finish":0,"allocation_count_start":0,"allocation_count_finish":0,"duration":2.1666},{"name":"meta_request.log","payload":{"filename":"c:/work/adusu_std/app/pdfs/delivery_slip_landscape_pdf.rb","line":29,"method":"create","message":"  \u001b[1m\u001b[36mDeliverySlipDetailLargeClassification Load (1.2ms)\u001b[0m  \u001b[1m\u001b[34mSELECT DISTINCT \"delivery_slip_detail_large_classifications\".* FROM \"delivery_slip_detail_large_classifications\" INNER JOIN \"delivery_slip_headers\" ON \"delivery_slip_headers\".\"id\" = \"delivery_slip_detail_large_classifications\".\"delivery_slip_header_id\" WHERE (delivery_slip_headers.id = '1471') ORDER BY \"delivery_slip_detail_large_classifications\".\"line_number\" ASC\u001b[0m","level":"debug"},"time":0,"transaction_id":0,"end":0,"children":[],"cpu_time_start":0,"cpu_time_finish":0,"allocation_count_start":0,"allocation_count_finish":0,"duration":0.0},{"name":"meta_request.log","payload":{"filename":"c:/work/adusu_std/app/pdfs/delivery_slip_landscape_pdf.rb","line":29,"method":"create","message":"  ↳ app/pdfs/delivery_slip_landscape_pdf.rb:29:in `create'","level":"debug"},"time":0,"transaction_id":0,"end":0,"children":[],"cpu_time_start":0,"cpu_time_finish":0,"allocation_count_start":0,"allocation_count_finish":0,"duration":0.0},{"name":"sql.active_record","payload":{"sql":"SELECT DISTINCT \"delivery_slip_detail_large_classifications\".* FROM \"delivery_slip_detail_large_classifications\" INNER JOIN \"delivery_slip_headers\" ON \"delivery_slip_headers\".\"id\" = \"delivery_slip_detail_large_classifications\".\"delivery_slip_header_id\" WHERE (delivery_slip_headers.id = '1471') ORDER BY \"delivery_slip_detail_large_classifications\".\"line_number\" ASC","name":"DeliverySlipDetailLargeClassification Load","binds":[],"type_casted_binds":[],"statement_name":null,"connection":"Not JSON Encodable","filename":"c:/work/adusu_std/app/pdfs/delivery_slip_landscape_pdf.rb","line":29,"method":"create"},"time":"2023-09-25T15:42:39.684+09:00","transaction_id":"66b1d48612a4b8ef2874","end":"2023-09-25T15:42:39.688+09:00","children":[],"cpu_time_start":0,"cpu_time_finish":0,"allocation_count_start":0,"allocation_count_finish":0,"duration":3.624},{"name":"meta_request.log","payload":{"filename":"c:/work/adusu_std/app/pdfs/delivery_slip_landscape_pdf.rb","line":52,"method":"block in create","message":"  \u001b[1m\u001b[36mDeliverySlipHeader Load (0.4ms)\u001b[0m  \u001b[1m\u001b[34mSELECT \"delivery_slip_headers\".* FROM \"delivery_slip_headers\" WHERE \"delivery_slip_headers\".\"id\" = $1 LIMIT $2\u001b[0m  [[\"id\", 1471], [\"LIMIT\", 1]]","level":"debug"},"time":0,"transaction_id":0,"end":0,"children":[],"cpu_time_start":0,"cpu_time_finish":0,"allocation_count_start":0,"allocation_count_finish":0,"duration":0.0},{"name":"meta_request.log","payload":{"filename":"c:/work/adusu_std/app/pdfs/delivery_slip_landscape_pdf.rb","line":52,"method":"block in create","message":"  ↳ app/pdfs/delivery_slip_landscape_pdf.rb:52:in `block in create'","level":"debug"},"time":0,"transaction_id":0,"end":0,"children":[],"cpu_time_start":0,"cpu_time_finish":0,"allocation_count_start":0,"allocation_count_finish":0,"duration":0.0},{"name":"sql.active_record","payload":{"sql":"SELECT \"delivery_slip_headers\".* FROM \"delivery_slip_headers\" WHERE \"delivery_slip_headers\".\"id\" = $1 LIMIT $2","name":"DeliverySlipHeader Load","binds":[{"name":"id","value_before_type_cast":1471,"type":{"precision":null,"scale":null,"limit":4,"range":"-2147483648...2147483648"},"original_attribute":null,"value":1471,"value_for_database":1471},{"name":"LIMIT","value_before_type_cast":1,"type":{"precision":null,"scale":null,"limit":null},"original_attribute":null,"value":1}],"type_casted_binds":[1471,1],"statement_name":"a1","connection":"Not JSON Encodable","filename":"c:/work/adusu_std/app/pdfs/delivery_slip_landscape_pdf.rb","line":52,"method":"block in create"},"time":"2023-09-25T15:42:39.689+09:00","transaction_id":"66b1d48612a4b8ef2874","end":"2023-09-25T15:42:39.690+09:00","children":[],"cpu_time_start":0,"cpu_time_finish":0,"allocation_count_start":0,"allocation_count_finish":0,"duration":1.5472000000000001},{"name":"meta_request.log","payload":{"filename":"c:/work/adusu_std/app/pdfs/delivery_slip_landscape_pdf.rb","line":54,"method":"block in create","message":"  \u001b[1m\u001b[36mConstructionDatum Exists? (0.8ms)\u001b[0m  \u001b[1m\u001b[34mSELECT 1 AS one FROM \"construction_data\" WHERE \"construction_data\".\"id\" = $1 LIMIT $2\u001b[0m  [[\"id\", 2658], [\"LIMIT\", 1]]","level":"debug"},"time":0,"transaction_id":0,"end":0,"children":[],"cpu_time_start":0,"cpu_time_finish":0,"allocation_count_start":0,"allocation_count_finish":0,"duration":0.0},{"name":"meta_request.log","payload":{"filename":"c:/work/adusu_std/app/pdfs/delivery_slip_landscape_pdf.rb","line":54,"method":"block in create","message":"  ↳ app/pdfs/delivery_slip_landscape_pdf.rb:54:in `block in create'","level":"debug"},"time":0,"transaction_id":0,"end":0,"children":[],"cpu_time_start":0,"cpu_time_finish":0,"allocation_count_start":0,"allocation_count_finish":0,"duration":0.0},{"name":"sql.active_record","payload":{"sql":"SELECT 1 AS one FROM \"construction_data\" WHERE \"construction_data\".\"id\" = $1 LIMIT $2","name":"ConstructionDatum Exists?","binds":[{"name":"id","value_before_type_cast":2658,"type":{"precision":null,"scale":null,"limit":4,"range":"-2147483648...2147483648"},"original_attribute":null,"_unboundable":null,"value":2658,"value_for_database":2658},{"name":"LIMIT","value_before_type_cast":1,"type":{"precision":null,"scale":null,"limit":null},"original_attribute":null,"value":1}],"type_casted_binds":[2658,1],"statement_name":null,"connection":"Not JSON Encodable","filename":"c:/work/adusu_std/app/pdfs/delivery_slip_landscape_pdf.rb","line":54,"method":"block in create"},"time":"2023-09-25T15:42:39.691+09:00","transaction_id":"66b1d48612a4b8ef2874","end":"2023-09-25T15:42:39.694+09:00","children":[],"cpu_time_start":0,"cpu_time_finish":0,"allocation_count_start":0,"allocation_count_finish":0,"duration":2.5860000000000003},{"name":"meta_request.log","payload":{"filename":"c:/work/adusu_std/app/pdfs/delivery_slip_landscape_pdf.rb","line":55,"method":"block in create","message":"  \u001b[1m\u001b[36mConstructionDatum Load (0.5ms)\u001b[0m  \u001b[1m\u001b[34mSELECT \"construction_data\".* FROM \"construction_data\" WHERE \"construction_data\".\"id\" = $1 LIMIT $2\u001b[0m  [[\"id\", 2658], [\"LIMIT\", 1]]","level":"debug"},"time":0,"transaction_id":0,"end":0,"children":[],"cpu_time_start":0,"cpu_time_finish":0,"allocation_count_start":0,"allocation_count_finish":0,"duration":0.0},{"name":"meta_request.log","payload":{"filename":"c:/work/adusu_std/app/pdfs/delivery_slip_landscape_pdf.rb","line":55,"method":"block in create","message":"  ↳ app/pdfs/delivery_slip_landscape_pdf.rb:55:in `block in create'","level":"debug"},"time":0,"transaction_id":0,"end":0,"children":[],"cpu_time_start":0,"cpu_time_finish":0,"allocation_count_start":0,"allocation_count_finish":0,"duration":0.0},{"name":"sql.active_record","payload":{"sql":"SELECT \"construction_data\".* FROM \"construction_data\" WHERE \"construction_data\".\"id\" = $1 LIMIT $2","name":"ConstructionDatum Load","binds":[{"name":"id","value_before_type_cast":2658,"type":{"precision":null,"scale":null,"limit":4,"range":"-2147483648...2147483648"},"original_attribute":null,"value":2658,"value_for_database":2658},{"name":"LIMIT","value_before_type_cast":1,"type":{"precision":null,"scale":null,"limit":null},"original_attribute":null,"value":1}],"type_casted_binds":[2658,1],"statement_name":"a9","connection":"Not JSON Encodable","filename":"c:/work/adusu_std/app/pdfs/delivery_slip_landscape_pdf.rb","line":55,"method":"block in create"},"time":"2023-09-25T15:42:39.695+09:00","transaction_id":"66b1d48612a4b8ef2874","end":"2023-09-25T15:42:39.697+09:00","children":[],"cpu_time_start":0,"cpu_time_finish":0,"allocation_count_start":0,"allocation_count_finish":0,"duration":1.5881},{"name":"meta_request.log","payload":{"filename":"c:/work/adusu_std/app/pdfs/delivery_slip_landscape_pdf.rb","line":58,"method":"block in create","message":"  \u001b[1m\u001b[36mCustomerMaster Load (0.4ms)\u001b[0m  \u001b[1m\u001b[34mSELECT \"customer_masters\".* FROM \"customer_masters\" WHERE \"customer_masters\".\"id\" = $1 ORDER BY \"customer_masters\".\"id\" ASC LIMIT $2\u001b[0m  [[\"id\", 86], [\"LIMIT\", 1]]","level":"debug"},"time":0,"transaction_id":0,"end":0,"children":[],"cpu_time_start":0,"cpu_time_finish":0,"allocation_count_start":0,"allocation_count_finish":0,"duration":0.0},{"name":"meta_request.log","payload":{"filename":"c:/work/adusu_std/app/pdfs/delivery_slip_landscape_pdf.rb","line":58,"method":"block in create","message":"  ↳ app/pdfs/delivery_slip_landscape_pdf.rb:58:in `block in create'","level":"debug"},"time":0,"transaction_id":0,"end":0,"children":[],"cpu_time_start":0,"cpu_time_finish":0,"allocation_count_start":0,"allocation_count_finish":0,"duration":0.0},{"name":"sql.active_record","payload":{"sql":"SELECT \"customer_masters\".* FROM \"customer_masters\" WHERE \"customer_masters\".\"id\" = $1 ORDER BY \"customer_masters\".\"id\" ASC LIMIT $2","name":"CustomerMaster Load","binds":[{"name":"id","value_before_type_cast":86,"type":{"precision":null,"scale":null,"limit":4,"range":"-2147483648...2147483648"},"original_attribute":null,"_unboundable":null,"value":86,"value_for_database":86},{"name":"LIMIT","value_before_type_cast":1,"type":{"precision":null,"scale":null,"limit":null},"original_attribute":null,"value":1}],"type_casted_binds":[86,1],"statement_name":"a12","connection":"Not JSON Encodable","filename":"c:/work/adusu_std/app/pdfs/delivery_slip_landscape_pdf.rb","line":58,"method":"block in create"},"time":"2023-09-25T15:42:39.698+09:00","transaction_id":"66b1d48612a4b8ef2874","end":"2023-09-25T15:42:39.700+09:00","children":[],"cpu_time_start":0,"cpu_time_finish":0,"allocation_count_start":0,"allocation_count_finish":0,"duration":1.8607},{"name":"meta_request.log","payload":{"filename":"c:/work/adusu_std/app/pdfs/delivery_slip_landscape_pdf.rb","line":152,"method":"block in create","message":"  \u001b[1m\u001b[36mCACHE CustomerMaster Load (0.0ms)\u001b[0m  \u001b[1m\u001b[34mSELECT \"customer_masters\".* FROM \"customer_masters\" WHERE \"customer_masters\".\"id\" = $1 LIMIT $2\u001b[0m  [[\"id\", 86], [\"LIMIT\", 1]]","level":"debug"},"time":0,"transaction_id":0,"end":0,"children":[],"cpu_time_start":0,"cpu_time_finish":0,"allocation_count_start":0,"allocation_count_finish":0,"duration":0.0},{"name":"meta_request.log","payload":{"filename":"c:/work/adusu_std/app/pdfs/delivery_slip_landscape_pdf.rb","line":152,"method":"block in create","message":"  ↳ app/pdfs/delivery_slip_landscape_pdf.rb:152:in `block in create'","level":"debug"},"time":0,"transaction_id":0,"end":0,"children":[],"cpu_time_start":0,"cpu_time_finish":0,"allocation_count_start":0,"allocation_count_finish":0,"duration":0.0},{"name":"sql.active_record","payload":{"sql":"SELECT \"customer_masters\".* FROM \"customer_masters\" WHERE \"customer_masters\".\"id\" = $1 LIMIT $2","binds":[{"name":"id","value_before_type_cast":86,"type":{"precision":null,"scale":null,"limit":4,"range":"-2147483648...2147483648"},"original_attribute":null,"value":86,"value_for_database":86},{"name":"LIMIT","value_before_type_cast":1,"type":{"precision":null,"scale":null,"limit":null},"original_attribute":null,"value":1}],"type_casted_binds":{},"name":"CustomerMaster Load","connection":"Not JSON Encodable","cached":true,"filename":"c:/work/adusu_std/app/pdfs/delivery_slip_landscape_pdf.rb","line":152,"method":"block in create"},"time":"2023-09-25T15:42:39.703+09:00","transaction_id":"c2c3e54eba86f291ec2a","end":"2023-09-25T15:42:39.705+09:00","children":[],"cpu_time_start":0,"cpu_time_finish":0,"allocation_count_start":0,"allocation_count_finish":0,"duration":2.105},{"name":"meta_request.log","payload":{"filename":"c:/work/adusu_std/app/pdfs/delivery_slip_landscape_pdf.rb","line":262,"method":"block (2 levels) in create","message":"  \u001b[1m\u001b[36mWorkingUnit Load (0.5ms)\u001b[0m  \u001b[1m\u001b[34mSELECT \"working_units\".* FROM \"working_units\" WHERE \"working_units\".\"id\" = $1 LIMIT $2\u001b[0m  [[\"id\", 22], [\"LIMIT\", 1]]","level":"debug"},"time":0,"transaction_id":0,"end":0,"children":[],"cpu_time_start":0,"cpu_time_finish":0,"allocation_count_start":0,"allocation_count_finish":0,"duration":0.0},{"name":"meta_request.log","payload":{"filename":"c:/work/adusu_std/app/pdfs/delivery_slip_landscape_pdf.rb","line":262,"method":"block (2 levels) in create","message":"  ↳ app/pdfs/delivery_slip_landscape_pdf.rb:262:in `block (2 levels) in create'","level":"debug"},"time":0,"transaction_id":0,"end":0,"children":[],"cpu_time_start":0,"cpu_time_finish":0,"allocation_count_start":0,"allocation_count_finish":0,"duration":0.0},{"name":"sql.active_record","payload":{"sql":"SELECT \"working_units\".* FROM \"working_units\" WHERE \"working_units\".\"id\" = $1 LIMIT $2","name":"WorkingUnit Load","binds":[{"name":"id","value_before_type_cast":22,"type":{"precision":null,"scale":null,"limit":4,"range":"-2147483648...2147483648"},"original_attribute":null,"value":22,"value_for_database":22},{"name":"LIMIT","value_before_type_cast":1,"type":{"precision":null,"scale":null,"limit":null},"original_attribute":null,"value":1}],"type_casted_binds":[22,1],"statement_name":"a10","connection":"Not JSON Encodable","filename":"c:/work/adusu_std/app/pdfs/delivery_slip_landscape_pdf.rb","line":262,"method":"block (2 levels) in create"},"time":"2023-09-25T15:42:39.706+09:00","transaction_id":"66b1d48612a4b8ef2874","end":"2023-09-25T15:42:39.707+09:00","children":[],"cpu_time_start":0,"cpu_time_finish":0,"allocation_count_start":0,"allocation_count_finish":0,"duration":1.4607999999999999},{"name":"meta_request.log","payload":{"filename":"c:/work/adusu_std/app/pdfs/delivery_slip_landscape_pdf.rb","line":262,"method":"block (2 levels) in create","message":"  \u001b[1m\u001b[36mWorkingUnit Load (0.7ms)\u001b[0m  \u001b[1m\u001b[34mSELECT \"working_units\".* FROM \"working_units\" WHERE \"working_units\".\"id\" = $1 LIMIT $2\u001b[0m  [[\"id\", 4], [\"LIMIT\", 1]]","level":"debug"},"time":0,"transaction_id":0,"end":0,"children":[],"cpu_time_start":0,"cpu_time_finish":0,"allocation_count_start":0,"allocation_count_finish":0,"duration":0.0},{"name":"meta_request.log","payload":{"filename":"c:/work/adusu_std/app/pdfs/delivery_slip_landscape_pdf.rb","line":262,"method":"block (2 levels) in create","message":"  ↳ app/pdfs/delivery_slip_landscape_pdf.rb:262:in `block (2 levels) in create'","level":"debug"},"time":0,"transaction_id":0,"end":0,"children":[],"cpu_time_start":0,"cpu_time_finish":0,"allocation_count_start":0,"allocation_count_finish":0,"duration":0.0},{"name":"sql.active_record","payload":{"sql":"SELECT \"working_units\".* FROM \"working_units\" WHERE \"working_units\".\"id\" = $1 LIMIT $2","name":"WorkingUnit Load","binds":[{"name":"id","value_before_type_cast":4,"type":{"precision":null,"scale":null,"limit":4,"range":"-2147483648...2147483648"},"original_attribute":null,"value":4,"value_for_database":4},{"name":"LIMIT","value_before_type_cast":1,"type":{"precision":null,"scale":null,"limit":null},"original_attribute":null,"value":1}],"type_casted_binds":[4,1],"statement_name":"a10","connection":"Not JSON Encodable","filename":"c:/work/adusu_std/app/pdfs/delivery_slip_landscape_pdf.rb","line":262,"method":"block (2 levels) in create"},"time":"2023-09-25T15:42:39.709+09:00","transaction_id":"66b1d48612a4b8ef2874","end":"2023-09-25T15:42:39.711+09:00","children":[],"cpu_time_start":0,"cpu_time_finish":0,"allocation_count_start":0,"allocation_count_finish":0,"duration":2.6172999999999997},{"name":"meta_request.log","payload":{"filename":"c:/work/adusu_std/app/pdfs/delivery_slip_landscape_pdf.rb","line":337,"method":"set_detail_data","message":"  \u001b[1m\u001b[36mCACHE DeliverySlipDetailLargeClassification Load (0.0ms)\u001b[0m  \u001b[1m\u001b[34mSELECT DISTINCT \"delivery_slip_detail_large_classifications\".* FROM \"delivery_slip_detail_large_classifications\" INNER JOIN \"delivery_slip_headers\" ON \"delivery_slip_headers\".\"id\" = \"delivery_slip_detail_large_classifications\".\"delivery_slip_header_id\" WHERE (delivery_slip_headers.id = '1471') ORDER BY \"delivery_slip_detail_large_classifications\".\"line_number\" ASC\u001b[0m","level":"debug"},"time":0,"transaction_id":0,"end":0,"children":[],"cpu_time_start":0,"cpu_time_finish":0,"allocation_count_start":0,"allocation_count_finish":0,"duration":0.0},{"name":"meta_request.log","payload":{"filename":"c:/work/adusu_std/app/pdfs/delivery_slip_landscape_pdf.rb","line":337,"method":"set_detail_data","message":"  ↳ app/pdfs/delivery_slip_landscape_pdf.rb:337:in `set_detail_data'","level":"debug"},"time":0,"transaction_id":0,"end":0,"children":[],"cpu_time_start":0,"cpu_time_finish":0,"allocation_count_start":0,"allocation_count_finish":0,"duration":0.0},{"name":"sql.active_record","payload":{"sql":"SELECT DISTINCT \"delivery_slip_detail_large_classifications\".* FROM \"delivery_slip_detail_large_classifications\" INNER JOIN \"delivery_slip_headers\" ON \"delivery_slip_headers\".\"id\" = \"delivery_slip_detail_large_classifications\".\"delivery_slip_header_id\" WHERE (delivery_slip_headers.id = '1471') ORDER BY \"delivery_slip_detail_large_classifications\".\"line_number\" ASC","binds":[],"type_casted_binds":{},"name":"DeliverySlipDetailLargeClassification Load","connection":"Not JSON Encodable","cached":true,"filename":"c:/work/adusu_std/app/pdfs/delivery_slip_landscape_pdf.rb","line":337,"method":"set_detail_data"},"time":"2023-09-25T15:42:39.713+09:00","transaction_id":"c2c3e54eba86f291ec2a","end":"2023-09-25T15:42:39.714+09:00","children":[],"cpu_time_start":0,"cpu_time_finish":0,"allocation_count_start":0,"allocation_count_finish":0,"duration":1.1095},{"name":"meta_request.log","payload":{"filename":"c:/work/adusu_std/app/pdfs/delivery_slip_landscape_pdf.rb","line":345,"method":"block in set_detail_data","message":"  \u001b[1m\u001b[36mDeliverySlipDetailMiddleClassification Load (1.1ms)\u001b[0m  \u001b[1m\u001b[34mSELECT \"delivery_slip_detail_middle_classifications\".* FROM \"delivery_slip_detail_middle_classifications\" WHERE \"delivery_slip_detail_middle_classifications\".\"delivery_slip_header_id\" = $1 AND \"delivery_slip_detail_middle_classifications\".\"delivery_slip_detail_large_classification_id\" = $2 AND (id is NOT NULL)\u001b[0m  [[\"delivery_slip_header_id\", 1471], [\"delivery_slip_detail_large_classification_id\", 3823]]","level":"debug"},"time":0,"transaction_id":0,"end":0,"children":[],"cpu_time_start":0,"cpu_time_finish":0,"allocation_count_start":0,"allocation_count_finish":0,"duration":0.0},{"name":"meta_request.log","payload":{"filename":"c:/work/adusu_std/app/pdfs/delivery_slip_landscape_pdf.rb","line":345,"method":"block in set_detail_data","message":"  ↳ app/pdfs/delivery_slip_landscape_pdf.rb:345:in `block in set_detail_data'","level":"debug"},"time":0,"transaction_id":0,"end":0,"children":[],"cpu_time_start":0,"cpu_time_finish":0,"allocation_count_start":0,"allocation_count_finish":0,"duration":0.0},{"name":"sql.active_record","payload":{"sql":"SELECT \"delivery_slip_detail_middle_classifications\".* FROM \"delivery_slip_detail_middle_classifications\" WHERE \"delivery_slip_detail_middle_classifications\".\"delivery_slip_header_id\" = $1 AND \"delivery_slip_detail_middle_classifications\".\"delivery_slip_detail_large_classification_id\" = $2 AND (id is NOT NULL)","name":"DeliverySlipDetailMiddleClassification Load","binds":[{"name":"delivery_slip_header_id","value_before_type_cast":1471,"type":{"precision":null,"scale":null,"limit":4,"range":"-2147483648...2147483648"},"original_attribute":null,"_unboundable":null,"value":1471,"value_for_database":1471},{"name":"delivery_slip_detail_large_classification_id","value_before_type_cast":3823,"type":{"precision":null,"scale":null,"limit":4,"range":"-2147483648...2147483648"},"original_attribute":null,"_unboundable":null,"value":3823,"value_for_database":3823}],"type_casted_binds":[1471,3823],"statement_name":null,"connection":"Not JSON Encodable","filename":"c:/work/adusu_std/app/pdfs/delivery_slip_landscape_pdf.rb","line":345,"method":"block in set_detail_data"},"time":"2023-09-25T15:42:39.715+09:00","transaction_id":"66b1d48612a4b8ef2874","end":"2023-09-25T15:42:39.718+09:00","children":[],"cpu_time_start":0,"cpu_time_finish":0,"allocation_count_start":0,"allocation_count_finish":0,"duration":2.7231},{"name":"meta_request.log","payload":{"filename":"c:/work/adusu_std/app/pdfs/delivery_slip_landscape_pdf.rb","line":345,"method":"block in set_detail_data","message":"  \u001b[1m\u001b[36mDeliverySlipDetailMiddleClassification Load (1.1ms)\u001b[0m  \u001b[1m\u001b[34mSELECT \"delivery_slip_detail_middle_classifications\".* FROM \"delivery_slip_detail_middle_classifications\" WHERE \"delivery_slip_detail_middle_classifications\".\"delivery_slip_header_id\" = $1 AND \"delivery_slip_detail_middle_classifications\".\"delivery_slip_detail_large_classification_id\" = $2 AND (id is NOT NULL)\u001b[0m  [[\"delivery_slip_header_id\", 1471], [\"delivery_slip_detail_large_classification_id\", 3913]]","level":"debug"},"time":0,"transaction_id":0,"end":0,"children":[],"cpu_time_start":0,"cpu_time_finish":0,"allocation_count_start":0,"allocation_count_finish":0,"duration":0.0},{"name":"meta_request.log","payload":{"filename":"c:/work/adusu_std/app/pdfs/delivery_slip_landscape_pdf.rb","line":345,"method":"block in set_detail_data","message":"  ↳ app/pdfs/delivery_slip_landscape_pdf.rb:345:in `block in set_detail_data'","level":"debug"},"time":0,"transaction_id":0,"end":0,"children":[],"cpu_time_start":0,"cpu_time_finish":0,"allocation_count_start":0,"allocation_count_finish":0,"duration":0.0},{"name":"sql.active_record","payload":{"sql":"SELECT \"delivery_slip_detail_middle_classifications\".* FROM \"delivery_slip_detail_middle_classifications\" WHERE \"delivery_slip_detail_middle_classifications\".\"delivery_slip_header_id\" = $1 AND \"delivery_slip_detail_middle_classifications\".\"delivery_slip_detail_large_classification_id\" = $2 AND (id is NOT NULL)","name":"DeliverySlipDetailMiddleClassification Load","binds":[{"name":"delivery_slip_header_id","value_before_type_cast":1471,"type":{"precision":null,"scale":null,"limit":4,"range":"-2147483648...2147483648"},"original_attribute":null,"_unboundable":null,"value":1471,"value_for_database":1471},{"name":"delivery_slip_detail_large_classification_id","value_before_type_cast":3913,"type":{"precision":null,"scale":null,"limit":4,"range":"-2147483648...2147483648"},"original_attribute":null,"_unboundable":null,"value":3913,"value_for_database":3913}],"type_casted_binds":[1471,3913],"statement_name":null,"connection":"Not JSON Encodable","filename":"c:/work/adusu_std/app/pdfs/delivery_slip_landscape_pdf.rb","line":345,"method":"block in set_detail_data"},"time":"2023-09-25T15:42:39.719+09:00","transaction_id":"66b1d48612a4b8ef2874","end":"2023-09-25T15:42:39.721+09:00","children":[],"cpu_time_start":0,"cpu_time_finish":0,"allocation_count_start":0,"allocation_count_finish":0,"duration":2.2415},{"name":"meta_request.log","payload":{"filename":"c:/work/adusu_std/app/pdfs/delivery_slip_landscape_pdf.rb","line":383,"method":"delivery_slip_detailed_statement_landscape","message":"  \u001b[1m\u001b[36mDeliverySlipDetailMiddleClassification Load (0.9ms)\u001b[0m  \u001b[1m\u001b[34mSELECT \"delivery_slip_detail_middle_classifications\".* FROM \"delivery_slip_detail_middle_classifications\" WHERE \"delivery_slip_detail_middle_classifications\".\"delivery_slip_header_id\" = $1 AND \"delivery_slip_detail_middle_classifications\".\"delivery_slip_detail_large_classification_id\" = $2 AND (id is NOT NULL) ORDER BY line_number asc\u001b[0m  [[\"delivery_slip_header_id\", 1471], [\"delivery_slip_detail_large_classification_id\", 3913]]","level":"debug"},"time":0,"transaction_id":0,"end":0,"children":[],"cpu_time_start":0,"cpu_time_finish":0,"allocation_count_start":0,"allocation_count_finish":0,"duration":0.0},{"name":"meta_request.log","payload":{"filename":"c:/work/adusu_std/app/pdfs/delivery_slip_landscape_pdf.rb","line":383,"method":"delivery_slip_detailed_statement_landscape","message":"  ↳ app/pdfs/delivery_slip_landscape_pdf.rb:383:in `delivery_slip_detailed_statement_landscape'","level":"debug"},"time":0,"transaction_id":0,"end":0,"children":[],"cpu_time_start":0,"cpu_time_finish":0,"allocation_count_start":0,"allocation_count_finish":0,"duration":0.0},{"name":"sql.active_record","payload":{"sql":"SELECT \"delivery_slip_detail_middle_classifications\".* FROM \"delivery_slip_detail_middle_classifications\" WHERE \"delivery_slip_detail_middle_classifications\".\"delivery_slip_header_id\" = $1 AND \"delivery_slip_detail_middle_classifications\".\"delivery_slip_detail_large_classification_id\" = $2 AND (id is NOT NULL) ORDER BY line_number asc","name":"DeliverySlipDetailMiddleClassification Load","binds":[{"name":"delivery_slip_header_id","value_before_type_cast":1471,"type":{"precision":null,"scale":null,"limit":4,"range":"-2147483648...2147483648"},"original_attribute":null,"_unboundable":null,"value":1471,"value_for_database":1471},{"name":"delivery_slip_detail_large_classification_id","value_before_type_cast":3913,"type":{"precision":null,"scale":null,"limit":4,"range":"-2147483648...2147483648"},"original_attribute":null,"_unboundable":null,"value":3913,"value_for_database":3913}],"type_casted_binds":[1471,3913],"statement_name":null,"connection":"Not JSON Encodable","filename":"c:/work/adusu_std/app/pdfs/delivery_slip_landscape_pdf.rb","line":383,"method":"delivery_slip_detailed_statement_landscape"},"time":"2023-09-25T15:42:39.724+09:00","transaction_id":"66b1d48612a4b8ef2874","end":"2023-09-25T15:42:39.727+09:00","children":[],"cpu_time_start":0,"cpu_time_finish":0,"allocation_count_start":0,"allocation_count_finish":0,"duration":2.7089000000000003},{"name":"meta_request.log","payload":{"filename":"c:/work/adusu_std/app/pdfs/delivery_slip_landscape_pdf.rb","line":387,"method":"block in delivery_slip_detailed_statement_landscape","message":"  \u001b[1m\u001b[36mCACHE DeliverySlipHeader Load (0.2ms)\u001b[0m  \u001b[1m\u001b[34mSELECT \"delivery_slip_headers\".* FROM \"delivery_slip_headers\" WHERE \"delivery_slip_headers\".\"id\" = $1 LIMIT $2\u001b[0m  [[\"id\", 1471], [\"LIMIT\", 1]]","level":"debug"},"time":0,"transaction_id":0,"end":0,"children":[],"cpu_time_start":0,"cpu_time_finish":0,"allocation_count_start":0,"allocation_count_finish":0,"duration":0.0},{"name":"meta_request.log","payload":{"filename":"c:/work/adusu_std/app/pdfs/delivery_slip_landscape_pdf.rb","line":387,"method":"block in delivery_slip_detailed_statement_landscape","message":"  ↳ app/pdfs/delivery_slip_landscape_pdf.rb:387:in `block in delivery_slip_detailed_statement_landscape'","level":"debug"},"time":0,"transaction_id":0,"end":0,"children":[],"cpu_time_start":0,"cpu_time_finish":0,"allocation_count_start":0,"allocation_count_finish":0,"duration":0.0},{"name":"sql.active_record","payload":{"sql":"SELECT \"delivery_slip_headers\".* FROM \"delivery_slip_headers\" WHERE \"delivery_slip_headers\".\"id\" = $1 LIMIT $2","binds":[{"name":"id","value_before_type_cast":1471,"type":{"precision":null,"scale":null,"limit":4,"range":"-2147483648...2147483648"},"original_attribute":null,"value":1471,"value_for_database":1471},{"name":"LIMIT","value_before_type_cast":1,"type":{"precision":null,"scale":null,"limit":null},"original_attribute":null,"value":1}],"type_casted_binds":{},"name":"DeliverySlipHeader Load","connection":"Not JSON Encodable","cached":true,"filename":"c:/work/adusu_std/app/pdfs/delivery_slip_landscape_pdf.rb","line":387,"method":"block in delivery_slip_detailed_statement_landscape"},"time":"2023-09-25T15:42:39.729+09:00","transaction_id":"c2c3e54eba86f291ec2a","end":"2023-09-25T15:42:39.731+09:00","children":[],"cpu_time_start":0,"cpu_time_finish":0,"allocation_count_start":0,"allocation_count_finish":0,"duration":2.2594999999999996},{"name":"meta_request.log","payload":{"filename":"c:/work/adusu_std/app/pdfs/delivery_slip_landscape_pdf.rb","line":406,"method":"block in delivery_slip_detailed_statement_landscape","message":"  \u001b[1m\u001b[36mDeliverySlipDetailLargeClassification Load (0.6ms)\u001b[0m  \u001b[1m\u001b[34mSELECT \"delivery_slip_detail_large_classifications\".* FROM \"delivery_slip_detail_large_classifications\" WHERE \"delivery_slip_detail_large_classifications\".\"id\" = $1 LIMIT $2\u001b[0m  [[\"id\", 3913], [\"LIMIT\", 1]]","level":"debug"},"time":0,"transaction_id":0,"end":0,"children":[],"cpu_time_start":0,"cpu_time_finish":0,"allocation_count_start":0,"allocation_count_finish":0,"duration":0.0},{"name":"meta_request.log","payload":{"filename":"c:/work/adusu_std/app/pdfs/delivery_slip_landscape_pdf.rb","line":406,"method":"block in delivery_slip_detailed_statement_landscape","message":"  ↳ app/pdfs/delivery_slip_landscape_pdf.rb:406:in `block in delivery_slip_detailed_statement_landscape'","level":"debug"},"time":0,"transaction_id":0,"end":0,"children":[],"cpu_time_start":0,"cpu_time_finish":0,"allocation_count_start":0,"allocation_count_finish":0,"duration":0.0},{"name":"sql.active_record","payload":{"sql":"SELECT \"delivery_slip_detail_large_classifications\".* FROM \"delivery_slip_detail_large_classifications\" WHERE \"delivery_slip_detail_large_classifications\".\"id\" = $1 LIMIT $2","name":"DeliverySlipDetailLargeClassification Load","binds":[{"name":"id","value_before_type_cast":3913,"type":{"precision":null,"scale":null,"limit":4,"range":"-2147483648...2147483648"},"original_attribute":null,"value":3913,"value_for_database":3913},{"name":"LIMIT","value_before_type_cast":1,"type":{"precision":null,"scale":null,"limit":null},"original_attribute":null,"value":1}],"type_casted_binds":[3913,1],"statement_name":"a11","connection":"Not JSON Encodable","filename":"c:/work/adusu_std/app/pdfs/delivery_slip_landscape_pdf.rb","line":406,"method":"block in delivery_slip_detailed_statement_landscape"},"time":"2023-09-25T15:42:39.733+09:00","transaction_id":"66b1d48612a4b8ef2874","end":"2023-09-25T15:42:39.735+09:00","children":[],"cpu_time_start":0,"cpu_time_finish":0,"allocation_count_start":0,"allocation_count_finish":0,"duration":2.0222},{"name":"meta_request.log","payload":{"filename":"c:/work/adusu_std/app/pdfs/delivery_slip_landscape_pdf.rb","line":453,"method":"block (2 levels) in delivery_slip_detailed_statement_landscape","message":"  \u001b[1m\u001b[36mCACHE WorkingUnit Load (0.0ms)\u001b[0m  \u001b[1m\u001b[34mSELECT \"working_units\".* FROM \"working_units\" WHERE \"working_units\".\"id\" = $1 LIMIT $2\u001b[0m  [[\"id\", 4], [\"LIMIT\", 1]]","level":"debug"},"time":0,"transaction_id":0,"end":0,"children":[],"cpu_time_start":0,"cpu_time_finish":0,"allocation_count_start":0,"allocation_count_finish":0,"duration":0.0},{"name":"meta_request.log","payload":{"filename":"c:/work/adusu_std/app/pdfs/delivery_slip_landscape_pdf.rb","line":453,"method":"block (2 levels) in delivery_slip_detailed_statement_landscape","message":"  ↳ app/pdfs/delivery_slip_landscape_pdf.rb:453:in `block (2 levels) in delivery_slip_detailed_statement_landscape'","level":"debug"},"time":0,"transaction_id":0,"end":0,"children":[],"cpu_time_start":0,"cpu_time_finish":0,"allocation_count_start":0,"allocation_count_finish":0,"duration":0.0},{"name":"sql.active_record","payload":{"sql":"SELECT \"working_units\".* FROM \"working_units\" WHERE \"working_units\".\"id\" = $1 LIMIT $2","binds":[{"name":"id","value_before_type_cast":4,"type":{"precision":null,"scale":null,"limit":4,"range":"-2147483648...2147483648"},"original_attribute":null,"value":4,"value_for_database":4},{"name":"LIMIT","value_before_type_cast":1,"type":{"precision":null,"scale":null,"limit":null},"original_attribute":null,"value":1}],"type_casted_binds":{},"name":"WorkingUnit Load","connection":"Not JSON Encodable","cached":true,"filename":"c:/work/adusu_std/app/pdfs/delivery_slip_landscape_pdf.rb","line":453,"method":"block (2 levels) in delivery_slip_detailed_statement_landscape"},"time":"2023-09-25T15:42:39.736+09:00","transaction_id":"c2c3e54eba86f291ec2a","end":"2023-09-25T15:42:39.737+09:00","children":[],"cpu_time_start":0,"cpu_time_finish":0,"allocation_count_start":0,"allocation_count_finish":0,"duration":0.9576},{"name":"meta_request.log","payload":{"filename":"c:/work/adusu_std/app/controllers/delivery_slip_detail_large_classifications_controller.rb","line":151,"method":"block (2 levels) in index","message":null,"level":"debug"},"time":0,"transaction_id":0,"end":0,"children":[],"cpu_time_start":0,"cpu_time_finish":0,"allocation_count_start":0,"allocation_count_finish":0,"duration":0.0},{"name":"meta_request.log","payload":{"filename":"c:/work/adusu_std/app/controllers/delivery_slip_detail_large_classifications_controller.rb","line":151,"method":"block (2 levels) in index","message":null,"level":"info"},"time":0,"transaction_id":0,"end":0,"children":[],"cpu_time_start":0,"cpu_time_finish":0,"allocation_count_start":0,"allocation_count_finish":0,"duration":0.0},{"name":"render_template.action_view","payload":{"identifier":"text template","layout":null},"time":"2023-09-25T15:42:40.488+09:00","transaction_id":"c2c3e54eba86f291ec2a","end":"2023-09-25T15:42:40.488+09:00","children":[],"cpu_time_start":0,"cpu_time_finish":0,"allocation_count_start":0,"allocation_count_finish":0,"duration":0.4103},{"name":"meta_request.log","payload":{"filename":"c:/work/adusu_std/app/controllers/delivery_slip_detail_large_classifications_controller.rb","line":151,"method":"block (2 levels) in index","message":null,"level":"info"},"time":0,"transaction_id":0,"end":0,"children":[],"cpu_time_start":0,"cpu_time_finish":0,"allocation_count_start":0,"allocation_count_finish":0,"duration":0.0},{"name":"process_action.action_controller","payload":{"controller":"DeliverySlipDetailLargeClassificationsController","action":"index","request":"Not JSON Encodable","params":{"delivery_slip_header_id":"1471","print_type":"2","controller":"delivery_slip_detail_large_classifications","action":"index","format":"pdf"},"headers":{"SCRIPT_NAME":"","QUERY_STRING":"delivery_slip_header_id=1471\u0026print_type=2","SERVER_SOFTWARE":"puma 6.3.0 Mugi No Toki Itaru","GATEWAY_INTERFACE":"CGI/1.2","REQUEST_METHOD":"GET","REQUEST_PATH":"/delivery_slip_detail_large_classifications.pdf","REQUEST_URI":"/delivery_slip_detail_large_classifications.pdf?delivery_slip_header_id=1471\u0026print_type=2","SERVER_PROTOCOL":"HTTP/1.1","HTTP_HOST":"localhost:3000","HTTP_CONNECTION":"keep-alive","HTTP_SEC_CH_UA":"\"Chromium\";v=\"116\", \"Not)A;Brand\";v=\"24\", \"Google Chrome\";v=\"116\"","HTTP_SEC_CH_UA_MOBILE":"?0","HTTP_SEC_CH_UA_PLATFORM":"\"Windows\"","HTTP_UPGRADE_INSECURE_REQUESTS":"1","HTTP_USER_AGENT":"Mozilla/5.0 (Windows NT 10.0; Win64; x64) AppleWebKit/537.36 (KHTML, like Gecko) Chrome/116.0.0.0 Safari/537.36","HTTP_ACCEPT":"text/html,application/xhtml+xml,application/xml;q=0.9,image/avif,image/webp,image/apng,*/*;q=0.8,application/signed-exchange;v=b3;q=0.7","HTTP_SEC_FETCH_SITE":"same-origin","HTTP_SEC_FETCH_MODE":"navigate","HTTP_SEC_FETCH_USER":"?1","HTTP_SEC_FETCH_DEST":"document","HTTP_REFERER":"http://localhost:3000/delivery_slip_detail_large_classifications?delivery_slip_header_id=1471\u0026delivery_slip_header_name=%E5%92%8C%E3%83%90%E3%83%AB%E3%80%80%E3%82%A2%E3%83%92%E3%83%AB%E3%80%80%E5%88%86%E9%9B%BB%E7%9B%A4%E4%BF%AE%E7%90%86","HTTP_ACCEPT_ENCODING":"gzip, deflate, br","HTTP_ACCEPT_LANGUAGE":"ja,en-US;q=0.9,en;q=0.8,zh-TW;q=0.7,zh;q=0.6","HTTP_COOKIE":"keep-position-%2Fconstruction_data=0; keep-position-%2Fquotation_headers=0; recent_search_history=%7B%22id_eq%22%3D%3E%22%22%2C+%22with_id%22%3D%3E%22%22%2C+%22customer_id_eq%22%3D%3E%22%22%7D; keep-position-%2Fdelivery_slip_headers=0; _adusu_session=MWFsbEdVQnBjeUFZL040TEU5TU1BNjdpaHRQMmFiTGVscmhIR2FNZ1FHWmpKa2xhMkRlWXRacDRzRy9UU0ZFY292Q25vVjNIMWRKQXJNcWFESnBqVnBmUWkva2Z0TU5uL2tuMlRhL3VGdDVEZFBZNzZ4bmtRd25rR0phQVFNZG9NRXdleW8rcWdwSU56MUJsYU1ZWFBPT1RTc3ozRTJvZVgwOGFtN3V2ZTZ2U0FpS1crSmJBc0crbmxZb2NIbDBYUmYxOVZNUlc1WXNhZVVkRnlHMzFLNExLWlFGVGhTNkJWaU1WbllPbUZYQT0tLVNEbDVkeTd0RWNyMHJ6OFNabmFYOWc9PQ%3D%3D--2f012c2cdafb13a257f7750c007c3ec59e4c4b3e","SERVER_NAME":"localhost","SERVER_PORT":"3000","PATH_INFO":"/delivery_slip_detail_large_classifications.pdf","REMOTE_ADDR":"::1","HTTP_VERSION":"HTTP/1.1","ROUTES_21000_SCRIPT_NAME":"","ORIGINAL_FULLPATH":"/delivery_slip_detail_large_classifications.pdf?delivery_slip_header_id=1471\u0026print_type=2","ORIGINAL_SCRIPT_NAME":""},"format":"pdf","method":"GET","path":"/delivery_slip_detail_large_classifications.pdf?delivery_slip_header_id=1471\u0026print_type=2","response":"Not JSON Encodable","status":200,"view_runtime":1.28249999761465,"db_runtime":10.466399995493703},"time":"2023-09-25T15:42:39.660+09:00","transaction_id":"c2c3e54eba86f291ec2a","end":"2023-09-25T15:42:40.489+09:00","children":[],"cpu_time_start":0,"cpu_time_finish":0,"allocation_count_start":0,"allocation_count_finish":0,"duration":829.4978}]