[{"name":"meta_request.log","payload":{"filename":"c:/work/adusu_std/app/controllers/outsourcing_data_controller.rb","line":1321,"method":"set_payment_flag","message":"  \u001b[1m\u001b[36mPurchaseDatum Load (0.5ms)\u001b[0m  \u001b[1m\u001b[34mSELECT \"purchase_data\".* FROM \"purchase_data\" WHERE \"purchase_data\".\"id\" = $1 LIMIT $2\u001b[0m  [[\"id\", 27379], [\"LIMIT\", 1]]","level":"debug"},"time":0,"transaction_id":0,"end":0,"children":[],"cpu_time_start":0,"cpu_time_finish":0,"allocation_count_start":0,"allocation_count_finish":0,"duration":0.0},{"name":"meta_request.log","payload":{"filename":"c:/work/adusu_std/app/controllers/outsourcing_data_controller.rb","line":1321,"method":"set_payment_flag","message":"  ↳ app/controllers/outsourcing_data_controller.rb:1321:in `set_payment_flag'","level":"debug"},"time":0,"transaction_id":0,"end":0,"children":[],"cpu_time_start":0,"cpu_time_finish":0,"allocation_count_start":0,"allocation_count_finish":0,"duration":0.0},{"name":"sql.active_record","payload":{"sql":"SELECT \"purchase_data\".* FROM \"purchase_data\" WHERE \"purchase_data\".\"id\" = $1 LIMIT $2","name":"PurchaseDatum Load","binds":[{"name":"id","value_before_type_cast":"27379","type":{"precision":null,"scale":null,"limit":4,"range":"-2147483648...2147483648"},"original_attribute":null,"value":"27379","value_for_database":27379},{"name":"LIMIT","value_before_type_cast":1,"type":{"precision":null,"scale":null,"limit":null},"original_attribute":null,"value":1}],"type_casted_binds":[27379,1],"statement_name":"a32","connection":"Not JSON Encodable","filename":"c:/work/adusu_std/app/controllers/outsourcing_data_controller.rb","line":1321,"method":"set_payment_flag"},"time":"2023-12-02T10:54:31.123+09:00","transaction_id":"6030713981090a278e89","end":"2023-12-02T10:54:31.125+09:00","children":[],"cpu_time_start":0,"cpu_time_finish":0,"allocation_count_start":0,"allocation_count_finish":0,"duration":1.9842000000000002},{"name":"meta_request.log","payload":{"filename":"c:/work/adusu_std/app/controllers/outsourcing_data_controller.rb","line":1328,"method":"set_payment_flag","message":"  \u001b[1m\u001b[36mOutsourcingCost Load (0.8ms)\u001b[0m  \u001b[1m\u001b[34mSELECT \"outsourcing_costs\".* FROM \"outsourcing_costs\" WHERE \"outsourcing_costs\".\"purchase_order_datum_id\" = $1 ORDER BY \"outsourcing_costs\".\"id\" ASC LIMIT $2\u001b[0m  [[\"purchase_order_datum_id\", 3904], [\"LIMIT\", 1]]","level":"debug"},"time":0,"transaction_id":0,"end":0,"children":[],"cpu_time_start":0,"cpu_time_finish":0,"allocation_count_start":0,"allocation_count_finish":0,"duration":0.0},{"name":"meta_request.log","payload":{"filename":"c:/work/adusu_std/app/controllers/outsourcing_data_controller.rb","line":1328,"method":"set_payment_flag","message":"  ↳ app/controllers/outsourcing_data_controller.rb:1328:in `set_payment_flag'","level":"debug"},"time":0,"transaction_id":0,"end":0,"children":[],"cpu_time_start":0,"cpu_time_finish":0,"allocation_count_start":0,"allocation_count_finish":0,"duration":0.0},{"name":"sql.active_record","payload":{"sql":"SELECT \"outsourcing_costs\".* FROM \"outsourcing_costs\" WHERE \"outsourcing_costs\".\"purchase_order_datum_id\" = $1 ORDER BY \"outsourcing_costs\".\"id\" ASC LIMIT $2","name":"OutsourcingCost Load","binds":[{"name":"purchase_order_datum_id","value_before_type_cast":3904,"type":{"precision":null,"scale":null,"limit":4,"range":"-2147483648...2147483648"},"original_attribute":null,"_unboundable":null,"value":3904,"value_for_database":3904},{"name":"LIMIT","value_before_type_cast":1,"type":{"precision":null,"scale":null,"limit":null},"original_attribute":null,"value":1}],"type_casted_binds":[3904,1],"statement_name":"a33","connection":"Not JSON Encodable","filename":"c:/work/adusu_std/app/controllers/outsourcing_data_controller.rb","line":1328,"method":"set_payment_flag"},"time":"2023-12-02T10:54:31.126+09:00","transaction_id":"6030713981090a278e89","end":"2023-12-02T10:54:31.128+09:00","children":[],"cpu_time_start":0,"cpu_time_finish":0,"allocation_count_start":0,"allocation_count_finish":0,"duration":2.1155000000000004},{"name":"meta_request.log","payload":{"filename":"c:/work/adusu_std/app/controllers/outsourcing_data_controller.rb","line":1340,"method":"set_payment_flag","message":"  \u001b[1m\u001b[36mTRANSACTION (0.4ms)\u001b[0m  \u001b[1m\u001b[35mBEGIN\u001b[0m","level":"debug"},"time":0,"transaction_id":0,"end":0,"children":[],"cpu_time_start":0,"cpu_time_finish":0,"allocation_count_start":0,"allocation_count_finish":0,"duration":0.0},{"name":"meta_request.log","payload":{"filename":"c:/work/adusu_std/app/controllers/outsourcing_data_controller.rb","line":1340,"method":"set_payment_flag","message":"  ↳ app/controllers/outsourcing_data_controller.rb:1340:in `set_payment_flag'","level":"debug"},"time":0,"transaction_id":0,"end":0,"children":[],"cpu_time_start":0,"cpu_time_finish":0,"allocation_count_start":0,"allocation_count_finish":0,"duration":0.0},{"name":"sql.active_record","payload":{"sql":"BEGIN","name":"TRANSACTION","binds":[],"type_casted_binds":[],"statement_name":null,"connection":"Not JSON Encodable","filename":"c:/work/adusu_std/app/controllers/outsourcing_data_controller.rb","line":1340,"method":"set_payment_flag"},"time":"2023-12-02T10:54:31.130+09:00","transaction_id":"6030713981090a278e89","end":"2023-12-02T10:54:31.132+09:00","children":[],"cpu_time_start":0,"cpu_time_finish":0,"allocation_count_start":0,"allocation_count_finish":0,"duration":1.7274},{"name":"meta_request.log","payload":{"filename":"c:/work/adusu_std/app/controllers/outsourcing_data_controller.rb","line":1340,"method":"set_payment_flag","message":"  \u001b[1m\u001b[36mOutsourcingCost Update (4.1ms)\u001b[0m  \u001b[1m\u001b[33mUPDATE \"outsourcing_costs\" SET \"payment_amount\" = $1, \"payment_date\" = $2, \"updated_at\" = $3 WHERE \"outsourcing_costs\".\"id\" = $4\u001b[0m  [[\"payment_amount\", 242000], [\"payment_date\", \"2023-12-04\"], [\"updated_at\", \"2023-12-02 10:54:31.130143\"], [\"id\", 1052]]","level":"debug"},"time":0,"transaction_id":0,"end":0,"children":[],"cpu_time_start":0,"cpu_time_finish":0,"allocation_count_start":0,"allocation_count_finish":0,"duration":0.0},{"name":"meta_request.log","payload":{"filename":"c:/work/adusu_std/app/controllers/outsourcing_data_controller.rb","line":1340,"method":"set_payment_flag","message":"  ↳ app/controllers/outsourcing_data_controller.rb:1340:in `set_payment_flag'","level":"debug"},"time":0,"transaction_id":0,"end":0,"children":[],"cpu_time_start":0,"cpu_time_finish":0,"allocation_count_start":0,"allocation_count_finish":0,"duration":0.0},{"name":"sql.active_record","payload":{"sql":"UPDATE \"outsourcing_costs\" SET \"payment_amount\" = $1, \"payment_date\" = $2, \"updated_at\" = $3 WHERE \"outsourcing_costs\".\"id\" = $4","name":"OutsourcingCost Update","binds":[{"name":"payment_amount","value_before_type_cast":242000,"type":{"precision":null,"scale":null,"limit":4,"range":"-2147483648...2147483648"},"original_attribute":null,"value":242000,"value_for_database":242000},{"name":"payment_date","value_before_type_cast":"2023-12-04","type":{"precision":null,"scale":null,"limit":null},"original_attribute":null,"value":"2023-12-04","value_for_database":"2023-12-04"},{"name":"updated_at","value_before_type_cast":"2023-12-02T10:54:31.130+09:00","type":{"precision":null,"scale":null,"limit":null},"original_attribute":null,"value":"2023-12-02T10:54:31.130+09:00","value_for_database":"2023-12-02T10:54:31.130+09:00"},{"name":"id","value_before_type_cast":1052,"type":{"precision":null,"scale":null,"limit":4,"range":"-2147483648...2147483648"},"original_attribute":null,"_unboundable":null,"value":1052,"value_for_database":1052}],"type_casted_binds":[242000,"2023-12-04","2023-12-02 10:54:31.130143",1052],"statement_name":null,"connection":"Not JSON Encodable","filename":"c:/work/adusu_std/app/controllers/outsourcing_data_controller.rb","line":1340,"method":"set_payment_flag"},"time":"2023-12-02T10:54:31.132+09:00","transaction_id":"6030713981090a278e89","end":"2023-12-02T10:54:31.138+09:00","children":[],"cpu_time_start":0,"cpu_time_finish":0,"allocation_count_start":0,"allocation_count_finish":0,"duration":5.3713},{"name":"meta_request.log","payload":{"filename":"c:/work/adusu_std/app/controllers/outsourcing_data_controller.rb","line":1340,"method":"set_payment_flag","message":"  \u001b[1m\u001b[36mTRANSACTION (0.4ms)\u001b[0m  \u001b[1m\u001b[35mCOMMIT\u001b[0m","level":"debug"},"time":0,"transaction_id":0,"end":0,"children":[],"cpu_time_start":0,"cpu_time_finish":0,"allocation_count_start":0,"allocation_count_finish":0,"duration":0.0},{"name":"meta_request.log","payload":{"filename":"c:/work/adusu_std/app/controllers/outsourcing_data_controller.rb","line":1340,"method":"set_payment_flag","message":"  ↳ app/controllers/outsourcing_data_controller.rb:1340:in `set_payment_flag'","level":"debug"},"time":0,"transaction_id":0,"end":0,"children":[],"cpu_time_start":0,"cpu_time_finish":0,"allocation_count_start":0,"allocation_count_finish":0,"duration":0.0},{"name":"sql.active_record","payload":{"sql":"COMMIT","name":"TRANSACTION","binds":[],"type_casted_binds":[],"statement_name":null,"connection":"Not JSON Encodable","filename":"c:/work/adusu_std/app/controllers/outsourcing_data_controller.rb","line":1340,"method":"set_payment_flag"},"time":"2023-12-02T10:54:31.139+09:00","transaction_id":"6030713981090a278e89","end":"2023-12-02T10:54:31.140+09:00","children":[],"cpu_time_start":0,"cpu_time_finish":0,"allocation_count_start":0,"allocation_count_finish":0,"duration":1.3301999999999998},{"name":"meta_request.log","payload":{"filename":"c:/work/adusu_std/app/controllers/outsourcing_data_controller.rb","line":1348,"method":"set_payment_flag","message":"  \u001b[1m\u001b[36mTRANSACTION (0.3ms)\u001b[0m  \u001b[1m\u001b[35mBEGIN\u001b[0m","level":"debug"},"time":0,"transaction_id":0,"end":0,"children":[],"cpu_time_start":0,"cpu_time_finish":0,"allocation_count_start":0,"allocation_count_finish":0,"duration":0.0},{"name":"meta_request.log","payload":{"filename":"c:/work/adusu_std/app/controllers/outsourcing_data_controller.rb","line":1348,"method":"set_payment_flag","message":"  ↳ app/controllers/outsourcing_data_controller.rb:1348:in `set_payment_flag'","level":"debug"},"time":0,"transaction_id":0,"end":0,"children":[],"cpu_time_start":0,"cpu_time_finish":0,"allocation_count_start":0,"allocation_count_finish":0,"duration":0.0},{"name":"sql.active_record","payload":{"sql":"BEGIN","name":"TRANSACTION","binds":[],"type_casted_binds":[],"statement_name":null,"connection":"Not JSON Encodable","filename":"c:/work/adusu_std/app/controllers/outsourcing_data_controller.rb","line":1348,"method":"set_payment_flag"},"time":"2023-12-02T10:54:31.141+09:00","transaction_id":"6030713981090a278e89","end":"2023-12-02T10:54:31.143+09:00","children":[],"cpu_time_start":0,"cpu_time_finish":0,"allocation_count_start":0,"allocation_count_finish":0,"duration":1.7794},{"name":"meta_request.log","payload":{"filename":"c:/work/adusu_std/app/controllers/outsourcing_data_controller.rb","line":1348,"method":"set_payment_flag","message":"  \u001b[1m\u001b[36mPurchaseDatum Update (1.1ms)\u001b[0m  \u001b[1m\u001b[33mUPDATE \"purchase_data\" SET \"outsourcing_payment_flag\" = $1, \"payment_date\" = $2, \"updated_at\" = $3 WHERE \"purchase_data\".\"id\" = $4\u001b[0m  [[\"outsourcing_payment_flag\", 1], [\"payment_date\", \"2023-12-04\"], [\"updated_at\", \"2023-12-02 10:54:31.140967\"], [\"id\", 27379]]","level":"debug"},"time":0,"transaction_id":0,"end":0,"children":[],"cpu_time_start":0,"cpu_time_finish":0,"allocation_count_start":0,"allocation_count_finish":0,"duration":0.0},{"name":"meta_request.log","payload":{"filename":"c:/work/adusu_std/app/controllers/outsourcing_data_controller.rb","line":1348,"method":"set_payment_flag","message":"  ↳ app/controllers/outsourcing_data_controller.rb:1348:in `set_payment_flag'","level":"debug"},"time":0,"transaction_id":0,"end":0,"children":[],"cpu_time_start":0,"cpu_time_finish":0,"allocation_count_start":0,"allocation_count_finish":0,"duration":0.0},{"name":"sql.active_record","payload":{"sql":"UPDATE \"purchase_data\" SET \"outsourcing_payment_flag\" = $1, \"payment_date\" = $2, \"updated_at\" = $3 WHERE \"purchase_data\".\"id\" = $4","name":"PurchaseDatum Update","binds":[{"name":"outsourcing_payment_flag","value_before_type_cast":1,"type":{"precision":null,"scale":null,"limit":4,"range":"-2147483648...2147483648"},"original_attribute":null,"value":1,"value_for_database":1},{"name":"payment_date","value_before_type_cast":"2023-12-04","type":{"precision":null,"scale":null,"limit":null},"original_attribute":null,"value":"2023-12-04","value_for_database":"2023-12-04"},{"name":"updated_at","value_before_type_cast":"2023-12-02T10:54:31.140+09:00","type":{"precision":null,"scale":null,"limit":null},"original_attribute":null,"value":"2023-12-02T10:54:31.140+09:00","value_for_database":"2023-12-02T10:54:31.140+09:00"},{"name":"id","value_before_type_cast":27379,"type":{"precision":null,"scale":null,"limit":4,"range":"-2147483648...2147483648"},"original_attribute":null,"_unboundable":null,"value":27379,"value_for_database":27379}],"type_casted_binds":[1,"2023-12-04","2023-12-02 10:54:31.140967",27379],"statement_name":null,"connection":"Not JSON Encodable","filename":"c:/work/adusu_std/app/controllers/outsourcing_data_controller.rb","line":1348,"method":"set_payment_flag"},"time":"2023-12-02T10:54:31.143+09:00","transaction_id":"6030713981090a278e89","end":"2023-12-02T10:54:31.147+09:00","children":[],"cpu_time_start":0,"cpu_time_finish":0,"allocation_count_start":0,"allocation_count_finish":0,"duration":3.3745},{"name":"meta_request.log","payload":{"filename":"c:/work/adusu_std/app/controllers/outsourcing_data_controller.rb","line":1348,"method":"set_payment_flag","message":"  \u001b[1m\u001b[36mTRANSACTION (0.8ms)\u001b[0m  \u001b[1m\u001b[35mCOMMIT\u001b[0m","level":"debug"},"time":0,"transaction_id":0,"end":0,"children":[],"cpu_time_start":0,"cpu_time_finish":0,"allocation_count_start":0,"allocation_count_finish":0,"duration":0.0},{"name":"meta_request.log","payload":{"filename":"c:/work/adusu_std/app/controllers/outsourcing_data_controller.rb","line":1348,"method":"set_payment_flag","message":"  ↳ app/controllers/outsourcing_data_controller.rb:1348:in `set_payment_flag'","level":"debug"},"time":0,"transaction_id":0,"end":0,"children":[],"cpu_time_start":0,"cpu_time_finish":0,"allocation_count_start":0,"allocation_count_finish":0,"duration":0.0},{"name":"sql.active_record","payload":{"sql":"COMMIT","name":"TRANSACTION","binds":[],"type_casted_binds":[],"statement_name":null,"connection":"Not JSON Encodable","filename":"c:/work/adusu_std/app/controllers/outsourcing_data_controller.rb","line":1348,"method":"set_payment_flag"},"time":"2023-12-02T10:54:31.148+09:00","transaction_id":"6030713981090a278e89","end":"2023-12-02T10:54:31.151+09:00","children":[],"cpu_time_start":0,"cpu_time_finish":0,"allocation_count_start":0,"allocation_count_finish":0,"duration":3.0644},{"name":"render_template.action_view","payload":{"identifier":"c:/work/adusu_std/app/views/outsourcing_data/set_payment_flag.js.erb","layout":null},"time":"2023-12-02T10:54:31.152+09:00","transaction_id":"61da1d5a17cefaf7de2a","end":"2023-12-02T10:54:31.153+09:00","children":[],"cpu_time_start":0,"cpu_time_finish":0,"allocation_count_start":0,"allocation_count_finish":0,"duration":0.3826},{"name":"process_action.action_controller","payload":{"controller":"OutsourcingDataController","action":"set_payment_flag","request":"Not JSON Encodable","params":{"id":"27379","flag":"1","payment_date":"2023/12/04","controller":"outsourcing_data","action":"set_payment_flag"},"headers":{"SCRIPT_NAME":"","QUERY_STRING":"id=27379\u0026flag=1\u0026payment_date=2023%2F12%2F04","SERVER_SOFTWARE":"puma 6.3.0 Mugi No Toki Itaru","GATEWAY_INTERFACE":"CGI/1.2","REQUEST_METHOD":"GET","REQUEST_PATH":"/outsourcing_datum/set_payment_flag","REQUEST_URI":"/outsourcing_datum/set_payment_flag?id=27379\u0026flag=1\u0026payment_date=2023%2F12%2F04","SERVER_PROTOCOL":"HTTP/1.1","HTTP_HOST":"localhost:3000","HTTP_CONNECTION":"keep-alive","HTTP_SEC_CH_UA":"\"Google Chrome\";v=\"119\", \"Chromium\";v=\"119\", \"Not?A_Brand\";v=\"24\"","HTTP_ACCEPT":"*/*","HTTP_X_CSRF_TOKEN":"zxac+hTjxBSXQoaiPRBV3RE9B0tKNBl6tU/OeVBkj/06ZpqNfutOxumrzXTR8POqykvYItTCSF8ZKTIhe3QpRw==","HTTP_X_REQUESTED_WITH":"XMLHttpRequest","HTTP_SEC_CH_UA_MOBILE":"?0","HTTP_USER_AGENT":"Mozilla/5.0 (Windows NT 10.0; Win64; x64) AppleWebKit/537.36 (KHTML, like Gecko) Chrome/119.0.0.0 Safari/537.36","HTTP_SEC_CH_UA_PLATFORM":"\"Windows\"","HTTP_SEC_FETCH_SITE":"same-origin","HTTP_SEC_FETCH_MODE":"cors","HTTP_SEC_FETCH_DEST":"empty","HTTP_REFERER":"http://localhost:3000/outsourcing_data?utf8=%E2%9C%93\u0026q%5Bsupplier_id_eq%5D=37\u0026q%5Bpurchase_date_gteq%5D=\u0026q%5Bpurchase_date_lteq%5D=\u0026q%5Bpayment_date_or_unpaid_payment_date_gteq%5D=\u0026q%5Bpayment_date_or_unpaid_payment_date_lteq%5D=\u0026q%5Bpayment_due_date_gteq%5D=\u0026q%5Bpayment_due_date_lteq%5D=\u0026q%5Bpurchase_order_datum_id_in%5D%5B%5D=\u0026q%5Bwith_construction%5D=\u0026q%5Bwith_customer%5D=\u0026q%5Boutsourcing_invoice_flag_eq%5D=\u0026q%5Boutsourcing_payment_flag_eq%5D=0\u0026commit=%E6%A4%9C%E7%B4%A2%28%E9%9B%86%E8%A8%88%29\u0026q%5Bpayment_date%5D=","HTTP_ACCEPT_ENCODING":"gzip, deflate, br","HTTP_ACCEPT_LANGUAGE":"ja,en-US;q=0.9,en;q=0.8,zh-TW;q=0.7,zh;q=0.6","HTTP_COOKIE":"keep-position-%2Fdelivery_slip_detail_middle_classifications=409.6000061035156; keep-position-%2Finvoice_headers=100; keep-position-%2Fquotation_headers=0; keep-position-%2Fpurchase_data=0; keep-position-%2Fdelivery_slip_headers=0; keep-position-%2Foutsourcing_data=0; recent_search_history_outsourcing=%7B%22purchase_order_datum_id_eq%22%3D%3E%223904%22%7D; recent_search_history_purchase=%7B%22supplier_id_eq%22%3D%3E%2237%22%2C+%22purchase_date_gteq%22%3D%3E%22%22%2C+%22purchase_date_lteq%22%3D%3E%22%22%2C+%22payment_date_or_unpaid_payment_date_gteq%22%3D%3E%22%22%2C+%22payment_date_or_unpaid_payment_date_lteq%22%3D%3E%22%22%2C+%22payment_due_date_gteq%22%3D%3E%22%22%2C+%22payment_due_date_lteq%22%3D%3E%22%22%2C+%22purchase_order_datum_id_in%22%3D%3E%5B%22%22%5D%2C+%22with_construction%22%3D%3E%22%22%2C+%22with_customer%22%3D%3E%22%22%2C+%22outsourcing_invoice_flag_eq%22%3D%3E%22%22%2C+%22outsourcing_payment_flag_eq%22%3D%3E%220%22%2C+%22payment_date%22%3D%3E%22%22%7D; _adusu_session=L2ducnVCNUVTV1JvQTE3eGdBckhvYjI0RHEyR0VXSWVRc1g2VmNkN2hNaVdZUGkvSExMWlVyYUZNZ2MvM0pFdm9XSUIvMGhlQjFJU3NMd01rV0dvQ0J5WHUyaUp3ZHlEdmJ1ZjI0V3RlRERjTThpU2g3NGxFQXRRSTZwcjB2ZWFCN2hNYlF0cHJNSUs4cU03MjJVK2hOOWpBTUk1L3JCZGRFUkpRb0dEWnQ0VzMyaGMwVnQwelQvYkxYaHBOQXZPTTZ0YVFjWTJUWkFsc2huWGk0VVJDZDFjQ2dmK2Vvd0IxQnpjcXVIQUtYOHhmZmZjOFhDYy9lc1pHUGV6aVh2OS0tZXBYVk0rWlBOeGpYMlBTU1NLdEw2Zz09--ae1bea11c1cd9c7ea12fa2778d49ee0241846990","SERVER_NAME":"localhost","SERVER_PORT":"3000","PATH_INFO":"/outsourcing_datum/set_payment_flag","REMOTE_ADDR":"::1","HTTP_VERSION":"HTTP/1.1","ROUTES_21000_SCRIPT_NAME":"","ORIGINAL_FULLPATH":"/outsourcing_datum/set_payment_flag?id=27379\u0026flag=1\u0026payment_date=2023%2F12%2F04","ORIGINAL_SCRIPT_NAME":""},"format":"*/*","method":"GET","path":"/outsourcing_datum/set_payment_flag?id=27379\u0026flag=1\u0026payment_date=2023%2F12%2F04","response":"Not JSON Encodable","status":200,"view_runtime":1.4293999411165714,"db_runtime":8.20870022289455},"time":"2023-12-02T10:54:31.122+09:00","transaction_id":"61da1d5a17cefaf7de2a","end":"2023-12-02T10:54:31.153+09:00","children":[],"cpu_time_start":0,"cpu_time_finish":0,"allocation_count_start":0,"allocation_count_finish":0,"duration":31.704900000000002}]